setup.py
webpy_jinja2.py
webpy_jinja2.egg-info/PKG-INFO
webpy_jinja2.egg-info/SOURCES.txt
webpy_jinja2.egg-info/dependency_links.txt
webpy_jinja2.egg-info/requires.txt
webpy_jinja2.egg-info/top_level.txt