Metadata-Version: 1.0
Name: webpy-jinja2
Version: 0.1.1
Summary: Library to provide Jinja2 templating support for web.py applications.
Home-page: UNKNOWN
Author: Anand Chitipothu
Author-email: anandology@gmail.com
License: BSD
Platform: any
